grok_unoffical_api/__init__.py
grok_unoffical_api/_example.py
grok_unoffical_api/_headers_manager.py
grok_unoffical_api/grok_client.py
grok_unoffical_api/grok_cookies.py
grok_unoffical_api/grok_payload.py
grok_unoffical_api/grok_response.py
grok_unoffical_api-0.1.1.dist-info/METADATA
grok_unoffical_api-0.1.1.dist-info/WHEEL
grok_unoffical_api-0.1.1.dist-info/top_level.txt
grok_unoffical_api-0.1.1.dist-info/RECORD
